sgqlc_schemas/__init__.py
sgqlc_schemas/github/__init__.py
sgqlc_schemas/github/schema.py
sgqlc_schemas/monday/__init__.py
sgqlc_schemas/monday/schema.py
sgqlc_schemas-0.1.0.dist-info/LICENSE
sgqlc_schemas-0.1.0.dist-info/METADATA
sgqlc_schemas-0.1.0.dist-info/WHEEL
sgqlc_schemas-0.1.0.dist-info/top_level.txt
sgqlc_schemas-0.1.0.dist-info/RECORD
