Metadata-Version: 2.1
Name: sgqlc-schemas
Version: 0.1.0
Summary: A set of schemas for sgqlc package
Home-page: https://github.com/Mogost/sgqlc-schemas
Author: Alexandr Artemyev
Author-email: mogost@aartemyev.ru
License: MIT
Keywords: sgqlc,schema,schemas,graphql,github,monday
Platform: UNKNOWN
Classifier: Development Status :: 4 - Beta
Classifier: Environment :: Console
Classifier: Environment :: Web Environment
Classifier: Intended Audience :: Developers
Classifier: License :: OSI Approved :: MIT License
Classifier: Operating System :: OS Independent
Classifier: Programming Language :: Python
Classifier: Programming Language :: Python :: 3
Classifier: Programming Language :: Python :: 3 :: Only
Classifier: Programming Language :: Python :: 3.5
Classifier: Programming Language :: Python :: 3.6
Classifier: Programming Language :: Python :: 3.7
Classifier: Programming Language :: Python :: 3.8
Classifier: Programming Language :: Python :: 3.9
Classifier: Topic :: Software Development
Classifier: Topic :: Utilities
Requires-Python: >=3.6
Requires-Dist: sgqlc
